gaia_cli.py
gaia/__init__.py
gaia/gaia.py
gaia/base/__init__.py
gaia/base/vendors/__init__.py
gaia/base/vendors/base.py
gaia/base/vendors/chat_gpt.py
gaia/base/vendors/co_here.py
gaia/base/vendors/vendors_manager.py
gaia/cli/.gitignore
gaia/cli/__init__.py
gaia/cli/allow_commands.py
gaia/cli/config.json
gaia/cli/cors_allowed_origins.json
gaia/cli/forcer_template.py
gaia/cli/labelizer_template.py
gaia/cli/main_template.py
gaia/cli/pipeline_template.py
gaia/cli/pipeline_test_template.py
gaia/cli/postprocess_template.py
gaia/cli/predictable_template.py
gaia/cli/predictor_template.py
gaia/cli/preprocess_template.py
gaia/cli/shared_artifacts_template.py
gaia/cli/schema/__init__.py
gaia/cli/schema/__init___template.py
gaia/cli/schema/inputs_template.py
gaia/cli/schema/outputs_template.py
gaia/cli/schema/test_input_template.py
gaia/cli/schema/test_output_template.py
gaia/cli/tester/__init__.py
gaia/cli/tester/dataset_template.py
gaia/cli/tester/evaluator_template.py
gaia/cli/tester/general_tester_template.py
gaia/cli/tester/reporter_template.py
gaia/cli/tester/tester_template.py
gaia/cli/tester/trainer_template.py
gaia/cli/tester/cloud_eval/.cloud_eval_env
gaia/cli/tester/cloud_eval/Dockerfile_base
gaia/cli/tester/cloud_eval/Dockerfile_batch_processor
gaia/cli/tester/cloud_eval/__init__.py
gaia/cli/tester/cloud_eval/auto_model_eval.sh
gaia/cli/tester/cloud_eval/batch_entrypoint.sh
gaia/cli/tester/cloud_eval/build_worker.sh
gaia/cli/tester/cloud_eval/cloud_eval_client.py
gaia/cli/tester/cloud_eval/create_ecr_repo_if_needed.sh
gaia/cli/tester/cloud_eval/dvc_download_artifacts_s3.sh
gaia/cli/tester/cloud_eval/eval_on_cloud.sh
gaia/cli/tester/cloud_eval/eval_on_cloud_proc.sh
gaia/cli/tester/cloud_eval/gunicorn.conf.py
gaia/cli/tester/cloud_eval/tag_version.sh
gaia/cli/tester/cloud_eval/untag_version.sh
gaia/cli/tester/deploy_files/Dockerfile
gaia/cli/tester/deploy_files/Jenkinsfile
gaia/cli/tester/deploy_files/Jenkinsfile_dozi
gaia/cli/tester/deploy_files/__init__.py
gaia_lib-0.0.2.dist-info/METADATA
gaia_lib-0.0.2.dist-info/WHEEL
gaia_lib-0.0.2.dist-info/entry_points.txt
gaia_lib-0.0.2.dist-info/top_level.txt
gaia_lib-0.0.2.dist-info/RECORD
